LICENSE
MANIFEST.in
README.rst
VERSION
requirements.txt
setup.py
src/cdumay_http_client/__init__.py
src/cdumay_http_client/client.py
src/cdumay_http_client/client_async.py
src/cdumay_http_client/errors.py
src/cdumay_http_client.egg-info/PKG-INFO
src/cdumay_http_client.egg-info/SOURCES.txt
src/cdumay_http_client.egg-info/dependency_links.txt
src/cdumay_http_client.egg-info/requires.txt
src/cdumay_http_client.egg-info/top_level.txt
src/cdumay_http_client.egg-info/zip-safe