Metadata-Version: 2.1
Name: cdumay-http-client
Version: 0.0.14
Summary: HTTP client
Home-page: https://github.com/cdumay/cdumay-http-client
Author: Cedric DUMAY
Author-email: cedric.dumay@gmail.com
License: BSD 3-Clause
Platform: UNKNOWN
Classifier: Programming Language :: Python
Provides-Extra: async
License-File: LICENSE
